LICENSE
MANIFEST.in
README.rst
setup.cfg
setup.py
mpsign/VERSION
mpsign/__init__.py
mpsign/cmd.py
mpsign/const.py
mpsign/core.py
mpsign/crypto.py
mpsign/exceptions.py
mpsign/util.py
mpsign.egg-info/PKG-INFO
mpsign.egg-info/SOURCES.txt
mpsign.egg-info/dependency_links.txt
mpsign.egg-info/entry_points.txt
mpsign.egg-info/not-zip-safe
mpsign.egg-info/requires.txt
mpsign.egg-info/top_level.txt