Metadata-Version: 1.1
Name: mpsign
Version: 1.5.4
Summary: a tool which signs your bars on Baidu Tieba
Home-page: https://github.com/abrasumente233/mpsign
Author: abrasumente mp
Author-email: abrasumentee@gmail.com
License: MIT
Platform: UNKNOWN
Classifier: Development Status :: 4 - Beta
Classifier: License :: OSI Approved :: MIT License
Classifier: Operating System :: OS Independent
Classifier: Intended Audience :: Developers
Classifier: Programming Language :: Python :: 3
Classifier: Topic :: Utilities
